grafte/__init__.py
grafte/chart.py
grafte/cli.py
grafte/lib/__init__.py
grafte/lib/canvas.py
grafte/lib/data.py
grafte-0.0.1.dist-info/METADATA
grafte-0.0.1.dist-info/WHEEL
grafte-0.0.1.dist-info/entry_points.txt
grafte-0.0.1.dist-info/top_level.txt
grafte-0.0.1.dist-info/RECORD
